{"frames": {

"Images_00000.png":
{
	"frame": {"x":0,"y":0,"w":134,"h":129},
	"rotated": false,
	"trimmed": false,
	"spriteSourceSize": {"x":0,"y":0,"w":134,"h":129},
	"sourceSize": {"w":134,"h":129}
},
"Images_00001.png":
{
	"frame": {"x":134,"y":0,"w":134,"h":129},
	"rotated": false,
	"trimmed": false,
	"spriteSourceSize": {"x":0,"y":0,"w":134,"h":129},
	"sourceSize": {"w":134,"h":129}
},
"Images_00002.png":
{
	"frame": {"x":268,"y":0,"w":134,"h":129},
	"rotated": false,
	"trimmed": false,
	"spriteSourceSize": {"x":0,"y":0,"w":134,"h":129},
	"sourceSize": {"w":134,"h":129}
},
"Images_00003.png":
{
	"frame": {"x":402,"y":0,"w":134,"h":129},
	"rotated": false,
	"trimmed": false,
	"spriteSourceSize": {"x":0,"y":0,"w":134,"h":129},
	"sourceSize": {"w":134,"h":129}
},
"Images_00004.png":
{
	"frame": {"x":536,"y":0,"w":134,"h":129},
	"rotated": false,
	"trimmed": false,
	"spriteSourceSize": {"x":0,"y":0,"w":134,"h":129},
	"sourceSize": {"w":134,"h":129}
},
"Images_00005.png":
{
	"frame": {"x":670,"y":0,"w":134,"h":129},
	"rotated": false,
	"trimmed": false,
	"spriteSourceSize": {"x":0,"y":0,"w":134,"h":129},
	"sourceSize": {"w":134,"h":129}
},
"Images_00006.png":
{
	"frame": {"x":804,"y":0,"w":134,"h":129},
	"rotated": false,
	"trimmed": false,
	"spriteSourceSize": {"x":0,"y":0,"w":134,"h":129},
	"sourceSize": {"w":134,"h":129}
},
"Images_00007.png":
{
	"frame": {"x":938,"y":0,"w":134,"h":129},
	"rotated": false,
	"trimmed": false,
	"spriteSourceSize": {"x":0,"y":0,"w":134,"h":129},
	"sourceSize": {"w":134,"h":129}
},
"Images_00008.png":
{
	"frame": {"x":1072,"y":0,"w":134,"h":129},
	"rotated": false,
	"trimmed": false,
	"spriteSourceSize": {"x":0,"y":0,"w":134,"h":129},
	"sourceSize": {"w":134,"h":129}
},
"Images_00009.png":
{
	"frame": {"x":1206,"y":0,"w":134,"h":129},
	"rotated": false,
	"trimmed": false,
	"spriteSourceSize": {"x":0,"y":0,"w":134,"h":129},
	"sourceSize": {"w":134,"h":129}
},
"Images_00010.png":
{
	"frame": {"x":1340,"y":0,"w":134,"h":129},
	"rotated": false,
	"trimmed": false,
	"spriteSourceSize": {"x":0,"y":0,"w":134,"h":129},
	"sourceSize": {"w":134,"h":129}
},
"Images_00011.png":
{
	"frame": {"x":1474,"y":0,"w":134,"h":129},
	"rotated": false,
	"trimmed": false,
	"spriteSourceSize": {"x":0,"y":0,"w":134,"h":129},
	"sourceSize": {"w":134,"h":129}
},
"Images_00012.png":
{
	"frame": {"x":1608,"y":0,"w":134,"h":129},
	"rotated": false,
	"trimmed": false,
	"spriteSourceSize": {"x":0,"y":0,"w":134,"h":129},
	"sourceSize": {"w":134,"h":129}
},
"Images_00013.png":
{
	"frame": {"x":1742,"y":0,"w":134,"h":129},
	"rotated": false,
	"trimmed": false,
	"spriteSourceSize": {"x":0,"y":0,"w":134,"h":129},
	"sourceSize": {"w":134,"h":129}
},
"Images_00014.png":
{
	"frame": {"x":1876,"y":0,"w":134,"h":129},
	"rotated": false,
	"trimmed": false,
	"spriteSourceSize": {"x":0,"y":0,"w":134,"h":129},
	"sourceSize": {"w":134,"h":129}
},
"Images_00015.png":
{
	"frame": {"x":0,"y":129,"w":134,"h":129},
	"rotated": false,
	"trimmed": false,
	"spriteSourceSize": {"x":0,"y":0,"w":134,"h":129},
	"sourceSize": {"w":134,"h":129}
},
"Images_00016.png":
{
	"frame": {"x":134,"y":129,"w":134,"h":129},
	"rotated": false,
	"trimmed": false,
	"spriteSourceSize": {"x":0,"y":0,"w":134,"h":129},
	"sourceSize": {"w":134,"h":129}
},
"Images_00017.png":
{
	"frame": {"x":268,"y":129,"w":134,"h":129},
	"rotated": false,
	"trimmed": false,
	"spriteSourceSize": {"x":0,"y":0,"w":134,"h":129},
	"sourceSize": {"w":134,"h":129}
},
"Images_00018.png":
{
	"frame": {"x":402,"y":129,"w":134,"h":129},
	"rotated": false,
	"trimmed": false,
	"spriteSourceSize": {"x":0,"y":0,"w":134,"h":129},
	"sourceSize": {"w":134,"h":129}
},
"Images_00019.png":
{
	"frame": {"x":536,"y":129,"w":134,"h":129},
	"rotated": false,
	"trimmed": false,
	"spriteSourceSize": {"x":0,"y":0,"w":134,"h":129},
	"sourceSize": {"w":134,"h":129}
},
"Images_00020.png":
{
	"frame": {"x":670,"y":129,"w":134,"h":129},
	"rotated": false,
	"trimmed": false,
	"spriteSourceSize": {"x":0,"y":0,"w":134,"h":129},
	"sourceSize": {"w":134,"h":129}
},
"Images_00021.png":
{
	"frame": {"x":804,"y":129,"w":134,"h":129},
	"rotated": false,
	"trimmed": false,
	"spriteSourceSize": {"x":0,"y":0,"w":134,"h":129},
	"sourceSize": {"w":134,"h":129}
},
"Images_00022.png":
{
	"frame": {"x":938,"y":129,"w":134,"h":129},
	"rotated": false,
	"trimmed": false,
	"spriteSourceSize": {"x":0,"y":0,"w":134,"h":129},
	"sourceSize": {"w":134,"h":129}
},
"Images_00023.png":
{
	"frame": {"x":1072,"y":129,"w":134,"h":129},
	"rotated": false,
	"trimmed": false,
	"spriteSourceSize": {"x":0,"y":0,"w":134,"h":129},
	"sourceSize": {"w":134,"h":129}
},
"Images_00024.png":
{
	"frame": {"x":1206,"y":129,"w":134,"h":129},
	"rotated": false,
	"trimmed": false,
	"spriteSourceSize": {"x":0,"y":0,"w":134,"h":129},
	"sourceSize": {"w":134,"h":129}
},
"Images_00025.png":
{
	"frame": {"x":1340,"y":129,"w":134,"h":129},
	"rotated": false,
	"trimmed": false,
	"spriteSourceSize": {"x":0,"y":0,"w":134,"h":129},
	"sourceSize": {"w":134,"h":129}
},
"Images_00026.png":
{
	"frame": {"x":1474,"y":129,"w":134,"h":129},
	"rotated": false,
	"trimmed": false,
	"spriteSourceSize": {"x":0,"y":0,"w":134,"h":129},
	"sourceSize": {"w":134,"h":129}
},
"Images_00027.png":
{
	"frame": {"x":1608,"y":129,"w":134,"h":129},
	"rotated": false,
	"trimmed": false,
	"spriteSourceSize": {"x":0,"y":0,"w":134,"h":129},
	"sourceSize": {"w":134,"h":129}
},
"Images_00028.png":
{
	"frame": {"x":1742,"y":129,"w":134,"h":129},
	"rotated": false,
	"trimmed": false,
	"spriteSourceSize": {"x":0,"y":0,"w":134,"h":129},
	"sourceSize": {"w":134,"h":129}
},
"Images_00029.png":
{
	"frame": {"x":1876,"y":129,"w":134,"h":129},
	"rotated": false,
	"trimmed": false,
	"spriteSourceSize": {"x":0,"y":0,"w":134,"h":129},
	"sourceSize": {"w":134,"h":129}
},
"Images_00030.png":
{
	"frame": {"x":0,"y":258,"w":134,"h":129},
	"rotated": false,
	"trimmed": false,
	"spriteSourceSize": {"x":0,"y":0,"w":134,"h":129},
	"sourceSize": {"w":134,"h":129}
},
"Images_00031.png":
{
	"frame": {"x":134,"y":258,"w":134,"h":129},
	"rotated": false,
	"trimmed": false,
	"spriteSourceSize": {"x":0,"y":0,"w":134,"h":129},
	"sourceSize": {"w":134,"h":129}
},
"Images_00032.png":
{
	"frame": {"x":268,"y":258,"w":134,"h":129},
	"rotated": false,
	"trimmed": false,
	"spriteSourceSize": {"x":0,"y":0,"w":134,"h":129},
	"sourceSize": {"w":134,"h":129}
},
"Images_00033.png":
{
	"frame": {"x":402,"y":258,"w":134,"h":129},
	"rotated": false,
	"trimmed": false,
	"spriteSourceSize": {"x":0,"y":0,"w":134,"h":129},
	"sourceSize": {"w":134,"h":129}
},
"Images_00034.png":
{
	"frame": {"x":536,"y":258,"w":134,"h":129},
	"rotated": false,
	"trimmed": false,
	"spriteSourceSize": {"x":0,"y":0,"w":134,"h":129},
	"sourceSize": {"w":134,"h":129}
},
"Images_00035.png":
{
	"frame": {"x":670,"y":258,"w":134,"h":129},
	"rotated": false,
	"trimmed": false,
	"spriteSourceSize": {"x":0,"y":0,"w":134,"h":129},
	"sourceSize": {"w":134,"h":129}
},
"Images_00036.png":
{
	"frame": {"x":804,"y":258,"w":134,"h":129},
	"rotated": false,
	"trimmed": false,
	"spriteSourceSize": {"x":0,"y":0,"w":134,"h":129},
	"sourceSize": {"w":134,"h":129}
},
"Images_00037.png":
{
	"frame": {"x":938,"y":258,"w":134,"h":129},
	"rotated": false,
	"trimmed": false,
	"spriteSourceSize": {"x":0,"y":0,"w":134,"h":129},
	"sourceSize": {"w":134,"h":129}
},
"Images_00038.png":
{
	"frame": {"x":1072,"y":258,"w":134,"h":129},
	"rotated": false,
	"trimmed": false,
	"spriteSourceSize": {"x":0,"y":0,"w":134,"h":129},
	"sourceSize": {"w":134,"h":129}
},
"Images_00039.png":
{
	"frame": {"x":1206,"y":258,"w":134,"h":129},
	"rotated": false,
	"trimmed": false,
	"spriteSourceSize": {"x":0,"y":0,"w":134,"h":129},
	"sourceSize": {"w":134,"h":129}
},
"Images_00040.png":
{
	"frame": {"x":1340,"y":258,"w":134,"h":129},
	"rotated": false,
	"trimmed": false,
	"spriteSourceSize": {"x":0,"y":0,"w":134,"h":129},
	"sourceSize": {"w":134,"h":129}
},
"Images_00041.png":
{
	"frame": {"x":1474,"y":258,"w":134,"h":129},
	"rotated": false,
	"trimmed": false,
	"spriteSourceSize": {"x":0,"y":0,"w":134,"h":129},
	"sourceSize": {"w":134,"h":129}
},
"Images_00042.png":
{
	"frame": {"x":1608,"y":258,"w":134,"h":129},
	"rotated": false,
	"trimmed": false,
	"spriteSourceSize": {"x":0,"y":0,"w":134,"h":129},
	"sourceSize": {"w":134,"h":129}
},
"Images_00043.png":
{
	"frame": {"x":1742,"y":258,"w":134,"h":129},
	"rotated": false,
	"trimmed": false,
	"spriteSourceSize": {"x":0,"y":0,"w":134,"h":129},
	"sourceSize": {"w":134,"h":129}
},
"Images_00044.png":
{
	"frame": {"x":1876,"y":258,"w":134,"h":129},
	"rotated": false,
	"trimmed": false,
	"spriteSourceSize": {"x":0,"y":0,"w":134,"h":129},
	"sourceSize": {"w":134,"h":129}
},
"Images_00045.png":
{
	"frame": {"x":0,"y":387,"w":134,"h":129},
	"rotated": false,
	"trimmed": false,
	"spriteSourceSize": {"x":0,"y":0,"w":134,"h":129},
	"sourceSize": {"w":134,"h":129}
},
"Images_00046.png":
{
	"frame": {"x":134,"y":387,"w":134,"h":129},
	"rotated": false,
	"trimmed": false,
	"spriteSourceSize": {"x":0,"y":0,"w":134,"h":129},
	"sourceSize": {"w":134,"h":129}
},
"Images_00047.png":
{
	"frame": {"x":268,"y":387,"w":134,"h":129},
	"rotated": false,
	"trimmed": false,
	"spriteSourceSize": {"x":0,"y":0,"w":134,"h":129},
	"sourceSize": {"w":134,"h":129}
},
"Images_00048.png":
{
	"frame": {"x":402,"y":387,"w":134,"h":129},
	"rotated": false,
	"trimmed": false,
	"spriteSourceSize": {"x":0,"y":0,"w":134,"h":129},
	"sourceSize": {"w":134,"h":129}
},
"Images_00049.png":
{
	"frame": {"x":536,"y":387,"w":134,"h":129},
	"rotated": false,
	"trimmed": false,
	"spriteSourceSize": {"x":0,"y":0,"w":134,"h":129},
	"sourceSize": {"w":134,"h":129}
},
"Images_00050.png":
{
	"frame": {"x":670,"y":387,"w":134,"h":129},
	"rotated": false,
	"trimmed": false,
	"spriteSourceSize": {"x":0,"y":0,"w":134,"h":129},
	"sourceSize": {"w":134,"h":129}
},
"Images_00051.png":
{
	"frame": {"x":804,"y":387,"w":134,"h":129},
	"rotated": false,
	"trimmed": false,
	"spriteSourceSize": {"x":0,"y":0,"w":134,"h":129},
	"sourceSize": {"w":134,"h":129}
},
"Images_00052.png":
{
	"frame": {"x":938,"y":387,"w":134,"h":129},
	"rotated": false,
	"trimmed": false,
	"spriteSourceSize": {"x":0,"y":0,"w":134,"h":129},
	"sourceSize": {"w":134,"h":129}
},
"Images_00053.png":
{
	"frame": {"x":1072,"y":387,"w":134,"h":129},
	"rotated": false,
	"trimmed": false,
	"spriteSourceSize": {"x":0,"y":0,"w":134,"h":129},
	"sourceSize": {"w":134,"h":129}
},
"Images_00054.png":
{
	"frame": {"x":1206,"y":387,"w":134,"h":129},
	"rotated": false,
	"trimmed": false,
	"spriteSourceSize": {"x":0,"y":0,"w":134,"h":129},
	"sourceSize": {"w":134,"h":129}
},
"Images_00055.png":
{
	"frame": {"x":1340,"y":387,"w":134,"h":129},
	"rotated": false,
	"trimmed": false,
	"spriteSourceSize": {"x":0,"y":0,"w":134,"h":129},
	"sourceSize": {"w":134,"h":129}
},
"Images_00056.png":
{
	"frame": {"x":1474,"y":387,"w":134,"h":129},
	"rotated": false,
	"trimmed": false,
	"spriteSourceSize": {"x":0,"y":0,"w":134,"h":129},
	"sourceSize": {"w":134,"h":129}
},
"Images_00057.png":
{
	"frame": {"x":1608,"y":387,"w":134,"h":129},
	"rotated": false,
	"trimmed": false,
	"spriteSourceSize": {"x":0,"y":0,"w":134,"h":129},
	"sourceSize": {"w":134,"h":129}
},
"Images_00058.png":
{
	"frame": {"x":1742,"y":387,"w":134,"h":129},
	"rotated": false,
	"trimmed": false,
	"spriteSourceSize": {"x":0,"y":0,"w":134,"h":129},
	"sourceSize": {"w":134,"h":129}
},
"Images_00059.png":
{
	"frame": {"x":1876,"y":387,"w":134,"h":129},
	"rotated": false,
	"trimmed": false,
	"spriteSourceSize": {"x":0,"y":0,"w":134,"h":129},
	"sourceSize": {"w":134,"h":129}
},
"Images_00060.png":
{
	"frame": {"x":0,"y":516,"w":134,"h":129},
	"rotated": false,
	"trimmed": false,
	"spriteSourceSize": {"x":0,"y":0,"w":134,"h":129},
	"sourceSize": {"w":134,"h":129}
},
"Images_00061.png":
{
	"frame": {"x":134,"y":516,"w":134,"h":129},
	"rotated": false,
	"trimmed": false,
	"spriteSourceSize": {"x":0,"y":0,"w":134,"h":129},
	"sourceSize": {"w":134,"h":129}
},
"Images_00062.png":
{
	"frame": {"x":268,"y":516,"w":134,"h":129},
	"rotated": false,
	"trimmed": false,
	"spriteSourceSize": {"x":0,"y":0,"w":134,"h":129},
	"sourceSize": {"w":134,"h":129}
},
"Images_00063.png":
{
	"frame": {"x":402,"y":516,"w":134,"h":129},
	"rotated": false,
	"trimmed": false,
	"spriteSourceSize": {"x":0,"y":0,"w":134,"h":129},
	"sourceSize": {"w":134,"h":129}
},
"Images_00064.png":
{
	"frame": {"x":536,"y":516,"w":134,"h":129},
	"rotated": false,
	"trimmed": false,
	"spriteSourceSize": {"x":0,"y":0,"w":134,"h":129},
	"sourceSize": {"w":134,"h":129}
},
"Images_00065.png":
{
	"frame": {"x":670,"y":516,"w":134,"h":129},
	"rotated": false,
	"trimmed": false,
	"spriteSourceSize": {"x":0,"y":0,"w":134,"h":129},
	"sourceSize": {"w":134,"h":129}
},
"Images_00066.png":
{
	"frame": {"x":804,"y":516,"w":134,"h":129},
	"rotated": false,
	"trimmed": false,
	"spriteSourceSize": {"x":0,"y":0,"w":134,"h":129},
	"sourceSize": {"w":134,"h":129}
},
"Images_00067.png":
{
	"frame": {"x":938,"y":516,"w":134,"h":129},
	"rotated": false,
	"trimmed": false,
	"spriteSourceSize": {"x":0,"y":0,"w":134,"h":129},
	"sourceSize": {"w":134,"h":129}
},
"Images_00068.png":
{
	"frame": {"x":1072,"y":516,"w":134,"h":129},
	"rotated": false,
	"trimmed": false,
	"spriteSourceSize": {"x":0,"y":0,"w":134,"h":129},
	"sourceSize": {"w":134,"h":129}
},
"Images_00069.png":
{
	"frame": {"x":1206,"y":516,"w":134,"h":129},
	"rotated": false,
	"trimmed": false,
	"spriteSourceSize": {"x":0,"y":0,"w":134,"h":129},
	"sourceSize": {"w":134,"h":129}
},
"Images_00070.png":
{
	"frame": {"x":1340,"y":516,"w":134,"h":129},
	"rotated": false,
	"trimmed": false,
	"spriteSourceSize": {"x":0,"y":0,"w":134,"h":129},
	"sourceSize": {"w":134,"h":129}
},
"Images_00071.png":
{
	"frame": {"x":1474,"y":516,"w":134,"h":129},
	"rotated": false,
	"trimmed": false,
	"spriteSourceSize": {"x":0,"y":0,"w":134,"h":129},
	"sourceSize": {"w":134,"h":129}
},
"Images_00072.png":
{
	"frame": {"x":1608,"y":516,"w":134,"h":129},
	"rotated": false,
	"trimmed": false,
	"spriteSourceSize": {"x":0,"y":0,"w":134,"h":129},
	"sourceSize": {"w":134,"h":129}
},
"Images_00073.png":
{
	"frame": {"x":1742,"y":516,"w":134,"h":129},
	"rotated": false,
	"trimmed": false,
	"spriteSourceSize": {"x":0,"y":0,"w":134,"h":129},
	"sourceSize": {"w":134,"h":129}
},
"Images_00074.png":
{
	"frame": {"x":1876,"y":516,"w":134,"h":129},
	"rotated": false,
	"trimmed": false,
	"spriteSourceSize": {"x":0,"y":0,"w":134,"h":129},
	"sourceSize": {"w":134,"h":129}
},
"Images_00075.png":
{
	"frame": {"x":0,"y":645,"w":134,"h":129},
	"rotated": false,
	"trimmed": false,
	"spriteSourceSize": {"x":0,"y":0,"w":134,"h":129},
	"sourceSize": {"w":134,"h":129}
},
"Images_00076.png":
{
	"frame": {"x":134,"y":645,"w":134,"h":129},
	"rotated": false,
	"trimmed": false,
	"spriteSourceSize": {"x":0,"y":0,"w":134,"h":129},
	"sourceSize": {"w":134,"h":129}
},
"Images_00077.png":
{
	"frame": {"x":268,"y":645,"w":134,"h":129},
	"rotated": false,
	"trimmed": false,
	"spriteSourceSize": {"x":0,"y":0,"w":134,"h":129},
	"sourceSize": {"w":134,"h":129}
},
"Images_00078.png":
{
	"frame": {"x":402,"y":645,"w":134,"h":129},
	"rotated": false,
	"trimmed": false,
	"spriteSourceSize": {"x":0,"y":0,"w":134,"h":129},
	"sourceSize": {"w":134,"h":129}
},
"Images_00079.png":
{
	"frame": {"x":536,"y":645,"w":134,"h":129},
	"rotated": false,
	"trimmed": false,
	"spriteSourceSize": {"x":0,"y":0,"w":134,"h":129},
	"sourceSize": {"w":134,"h":129}
},
"Images_00080.png":
{
	"frame": {"x":670,"y":645,"w":134,"h":129},
	"rotated": false,
	"trimmed": false,
	"spriteSourceSize": {"x":0,"y":0,"w":134,"h":129},
	"sourceSize": {"w":134,"h":129}
},
"Images_00081.png":
{
	"frame": {"x":804,"y":645,"w":134,"h":129},
	"rotated": false,
	"trimmed": false,
	"spriteSourceSize": {"x":0,"y":0,"w":134,"h":129},
	"sourceSize": {"w":134,"h":129}
},
"Images_00082.png":
{
	"frame": {"x":938,"y":645,"w":134,"h":129},
	"rotated": false,
	"trimmed": false,
	"spriteSourceSize": {"x":0,"y":0,"w":134,"h":129},
	"sourceSize": {"w":134,"h":129}
},
"Images_00083.png":
{
	"frame": {"x":1072,"y":645,"w":134,"h":129},
	"rotated": false,
	"trimmed": false,
	"spriteSourceSize": {"x":0,"y":0,"w":134,"h":129},
	"sourceSize": {"w":134,"h":129}
},
"Images_00084.png":
{
	"frame": {"x":1206,"y":645,"w":134,"h":129},
	"rotated": false,
	"trimmed": false,
	"spriteSourceSize": {"x":0,"y":0,"w":134,"h":129},
	"sourceSize": {"w":134,"h":129}
},
"Images_00085.png":
{
	"frame": {"x":1340,"y":645,"w":134,"h":129},
	"rotated": false,
	"trimmed": false,
	"spriteSourceSize": {"x":0,"y":0,"w":134,"h":129},
	"sourceSize": {"w":134,"h":129}
},
"Images_00086.png":
{
	"frame": {"x":1474,"y":645,"w":134,"h":129},
	"rotated": false,
	"trimmed": false,
	"spriteSourceSize": {"x":0,"y":0,"w":134,"h":129},
	"sourceSize": {"w":134,"h":129}
},
"Images_00087.png":
{
	"frame": {"x":1608,"y":645,"w":134,"h":129},
	"rotated": false,
	"trimmed": false,
	"spriteSourceSize": {"x":0,"y":0,"w":134,"h":129},
	"sourceSize": {"w":134,"h":129}
},
"Images_00088.png":
{
	"frame": {"x":1742,"y":645,"w":134,"h":129},
	"rotated": false,
	"trimmed": false,
	"spriteSourceSize": {"x":0,"y":0,"w":134,"h":129},
	"sourceSize": {"w":134,"h":129}
},
"Images_00089.png":
{
	"frame": {"x":1876,"y":645,"w":134,"h":129},
	"rotated": false,
	"trimmed": false,
	"spriteSourceSize": {"x":0,"y":0,"w":134,"h":129},
	"sourceSize": {"w":134,"h":129}
},
"Images_00090.png":
{
	"frame": {"x":0,"y":774,"w":134,"h":129},
	"rotated": false,
	"trimmed": false,
	"spriteSourceSize": {"x":0,"y":0,"w":134,"h":129},
	"sourceSize": {"w":134,"h":129}
},
"Images_00091.png":
{
	"frame": {"x":134,"y":774,"w":134,"h":129},
	"rotated": false,
	"trimmed": false,
	"spriteSourceSize": {"x":0,"y":0,"w":134,"h":129},
	"sourceSize": {"w":134,"h":129}
},
"Images_00092.png":
{
	"frame": {"x":268,"y":774,"w":134,"h":129},
	"rotated": false,
	"trimmed": false,
	"spriteSourceSize": {"x":0,"y":0,"w":134,"h":129},
	"sourceSize": {"w":134,"h":129}
},
"Images_00093.png":
{
	"frame": {"x":402,"y":774,"w":134,"h":129},
	"rotated": false,
	"trimmed": false,
	"spriteSourceSize": {"x":0,"y":0,"w":134,"h":129},
	"sourceSize": {"w":134,"h":129}
},
"Images_00094.png":
{
	"frame": {"x":536,"y":774,"w":134,"h":129},
	"rotated": false,
	"trimmed": false,
	"spriteSourceSize": {"x":0,"y":0,"w":134,"h":129},
	"sourceSize": {"w":134,"h":129}
},
"Images_00095.png":
{
	"frame": {"x":670,"y":774,"w":134,"h":129},
	"rotated": false,
	"trimmed": false,
	"spriteSourceSize": {"x":0,"y":0,"w":134,"h":129},
	"sourceSize": {"w":134,"h":129}
},
"Images_00096.png":
{
	"frame": {"x":804,"y":774,"w":134,"h":129},
	"rotated": false,
	"trimmed": false,
	"spriteSourceSize": {"x":0,"y":0,"w":134,"h":129},
	"sourceSize": {"w":134,"h":129}
},
"Images_00097.png":
{
	"frame": {"x":938,"y":774,"w":134,"h":129},
	"rotated": false,
	"trimmed": false,
	"spriteSourceSize": {"x":0,"y":0,"w":134,"h":129},
	"sourceSize": {"w":134,"h":129}
},
"Images_00098.png":
{
	"frame": {"x":1072,"y":774,"w":134,"h":129},
	"rotated": false,
	"trimmed": false,
	"spriteSourceSize": {"x":0,"y":0,"w":134,"h":129},
	"sourceSize": {"w":134,"h":129}
},
"Images_00099.png":
{
	"frame": {"x":1206,"y":774,"w":134,"h":129},
	"rotated": false,
	"trimmed": false,
	"spriteSourceSize": {"x":0,"y":0,"w":134,"h":129},
	"sourceSize": {"w":134,"h":129}
},
"Images_00100.png":
{
	"frame": {"x":1340,"y":774,"w":134,"h":129},
	"rotated": false,
	"trimmed": false,
	"spriteSourceSize": {"x":0,"y":0,"w":134,"h":129},
	"sourceSize": {"w":134,"h":129}
},
"Images_00101.png":
{
	"frame": {"x":1474,"y":774,"w":134,"h":129},
	"rotated": false,
	"trimmed": false,
	"spriteSourceSize": {"x":0,"y":0,"w":134,"h":129},
	"sourceSize": {"w":134,"h":129}
},
"Images_00102.png":
{
	"frame": {"x":1608,"y":774,"w":134,"h":129},
	"rotated": false,
	"trimmed": false,
	"spriteSourceSize": {"x":0,"y":0,"w":134,"h":129},
	"sourceSize": {"w":134,"h":129}
},
"Images_00103.png":
{
	"frame": {"x":1742,"y":774,"w":134,"h":129},
	"rotated": false,
	"trimmed": false,
	"spriteSourceSize": {"x":0,"y":0,"w":134,"h":129},
	"sourceSize": {"w":134,"h":129}
},
"Images_00104.png":
{
	"frame": {"x":1876,"y":774,"w":134,"h":129},
	"rotated": false,
	"trimmed": false,
	"spriteSourceSize": {"x":0,"y":0,"w":134,"h":129},
	"sourceSize": {"w":134,"h":129}
},
"Images_00105.png":
{
	"frame": {"x":0,"y":903,"w":134,"h":129},
	"rotated": false,
	"trimmed": false,
	"spriteSourceSize": {"x":0,"y":0,"w":134,"h":129},
	"sourceSize": {"w":134,"h":129}
},
"Images_00106.png":
{
	"frame": {"x":134,"y":903,"w":134,"h":129},
	"rotated": false,
	"trimmed": false,
	"spriteSourceSize": {"x":0,"y":0,"w":134,"h":129},
	"sourceSize": {"w":134,"h":129}
},
"Images_00107.png":
{
	"frame": {"x":268,"y":903,"w":134,"h":129},
	"rotated": false,
	"trimmed": false,
	"spriteSourceSize": {"x":0,"y":0,"w":134,"h":129},
	"sourceSize": {"w":134,"h":129}
},
"Images_00108.png":
{
	"frame": {"x":402,"y":903,"w":134,"h":129},
	"rotated": false,
	"trimmed": false,
	"spriteSourceSize": {"x":0,"y":0,"w":134,"h":129},
	"sourceSize": {"w":134,"h":129}
},
"Images_00109.png":
{
	"frame": {"x":536,"y":903,"w":134,"h":129},
	"rotated": false,
	"trimmed": false,
	"spriteSourceSize": {"x":0,"y":0,"w":134,"h":129},
	"sourceSize": {"w":134,"h":129}
},
"Images_00110.png":
{
	"frame": {"x":670,"y":903,"w":134,"h":129},
	"rotated": false,
	"trimmed": false,
	"spriteSourceSize": {"x":0,"y":0,"w":134,"h":129},
	"sourceSize": {"w":134,"h":129}
},
"Images_00111.png":
{
	"frame": {"x":804,"y":903,"w":134,"h":129},
	"rotated": false,
	"trimmed": false,
	"spriteSourceSize": {"x":0,"y":0,"w":134,"h":129},
	"sourceSize": {"w":134,"h":129}
},
"Images_00112.png":
{
	"frame": {"x":938,"y":903,"w":134,"h":129},
	"rotated": false,
	"trimmed": false,
	"spriteSourceSize": {"x":0,"y":0,"w":134,"h":129},
	"sourceSize": {"w":134,"h":129}
},
"Images_00113.png":
{
	"frame": {"x":1072,"y":903,"w":134,"h":129},
	"rotated": false,
	"trimmed": false,
	"spriteSourceSize": {"x":0,"y":0,"w":134,"h":129},
	"sourceSize": {"w":134,"h":129}
},
"Images_00114.png":
{
	"frame": {"x":1206,"y":903,"w":134,"h":129},
	"rotated": false,
	"trimmed": false,
	"spriteSourceSize": {"x":0,"y":0,"w":134,"h":129},
	"sourceSize": {"w":134,"h":129}
},
"Images_00115.png":
{
	"frame": {"x":1340,"y":903,"w":134,"h":129},
	"rotated": false,
	"trimmed": false,
	"spriteSourceSize": {"x":0,"y":0,"w":134,"h":129},
	"sourceSize": {"w":134,"h":129}
},
"Images_00116.png":
{
	"frame": {"x":1474,"y":903,"w":134,"h":129},
	"rotated": false,
	"trimmed": false,
	"spriteSourceSize": {"x":0,"y":0,"w":134,"h":129},
	"sourceSize": {"w":134,"h":129}
},
"Images_00117.png":
{
	"frame": {"x":1608,"y":903,"w":134,"h":129},
	"rotated": false,
	"trimmed": false,
	"spriteSourceSize": {"x":0,"y":0,"w":134,"h":129},
	"sourceSize": {"w":134,"h":129}
},
"Images_00118.png":
{
	"frame": {"x":1742,"y":903,"w":134,"h":129},
	"rotated": false,
	"trimmed": false,
	"spriteSourceSize": {"x":0,"y":0,"w":134,"h":129},
	"sourceSize": {"w":134,"h":129}
},
"Images_00119.png":
{
	"frame": {"x":1876,"y":903,"w":134,"h":129},
	"rotated": false,
	"trimmed": false,
	"spriteSourceSize": {"x":0,"y":0,"w":134,"h":129},
	"sourceSize": {"w":134,"h":129}
},
"Images_00120.png":
{
	"frame": {"x":0,"y":1032,"w":134,"h":129},
	"rotated": false,
	"trimmed": false,
	"spriteSourceSize": {"x":0,"y":0,"w":134,"h":129},
	"sourceSize": {"w":134,"h":129}
},
"Images_00121.png":
{
	"frame": {"x":134,"y":1032,"w":134,"h":129},
	"rotated": false,
	"trimmed": false,
	"spriteSourceSize": {"x":0,"y":0,"w":134,"h":129},
	"sourceSize": {"w":134,"h":129}
},
"Images_00122.png":
{
	"frame": {"x":268,"y":1032,"w":134,"h":129},
	"rotated": false,
	"trimmed": false,
	"spriteSourceSize": {"x":0,"y":0,"w":134,"h":129},
	"sourceSize": {"w":134,"h":129}
},
"Images_00123.png":
{
	"frame": {"x":402,"y":1032,"w":134,"h":129},
	"rotated": false,
	"trimmed": false,
	"spriteSourceSize": {"x":0,"y":0,"w":134,"h":129},
	"sourceSize": {"w":134,"h":129}
},
"Images_00124.png":
{
	"frame": {"x":536,"y":1032,"w":134,"h":129},
	"rotated": false,
	"trimmed": false,
	"spriteSourceSize": {"x":0,"y":0,"w":134,"h":129},
	"sourceSize": {"w":134,"h":129}
},
"Images_00125.png":
{
	"frame": {"x":670,"y":1032,"w":134,"h":129},
	"rotated": false,
	"trimmed": false,
	"spriteSourceSize": {"x":0,"y":0,"w":134,"h":129},
	"sourceSize": {"w":134,"h":129}
},
"Images_00126.png":
{
	"frame": {"x":804,"y":1032,"w":134,"h":129},
	"rotated": false,
	"trimmed": false,
	"spriteSourceSize": {"x":0,"y":0,"w":134,"h":129},
	"sourceSize": {"w":134,"h":129}
},
"Images_00127.png":
{
	"frame": {"x":938,"y":1032,"w":134,"h":129},
	"rotated": false,
	"trimmed": false,
	"spriteSourceSize": {"x":0,"y":0,"w":134,"h":129},
	"sourceSize": {"w":134,"h":129}
},
"Images_00128.png":
{
	"frame": {"x":1072,"y":1032,"w":134,"h":129},
	"rotated": false,
	"trimmed": false,
	"spriteSourceSize": {"x":0,"y":0,"w":134,"h":129},
	"sourceSize": {"w":134,"h":129}
},
"Images_00129.png":
{
	"frame": {"x":1206,"y":1032,"w":134,"h":129},
	"rotated": false,
	"trimmed": false,
	"spriteSourceSize": {"x":0,"y":0,"w":134,"h":129},
	"sourceSize": {"w":134,"h":129}
},
"Images_00130.png":
{
	"frame": {"x":1340,"y":1032,"w":134,"h":129},
	"rotated": false,
	"trimmed": false,
	"spriteSourceSize": {"x":0,"y":0,"w":134,"h":129},
	"sourceSize": {"w":134,"h":129}
},
"Images_00131.png":
{
	"frame": {"x":1474,"y":1032,"w":134,"h":129},
	"rotated": false,
	"trimmed": false,
	"spriteSourceSize": {"x":0,"y":0,"w":134,"h":129},
	"sourceSize": {"w":134,"h":129}
},
"Images_00132.png":
{
	"frame": {"x":1608,"y":1032,"w":134,"h":129},
	"rotated": false,
	"trimmed": false,
	"spriteSourceSize": {"x":0,"y":0,"w":134,"h":129},
	"sourceSize": {"w":134,"h":129}
},
"Images_00133.png":
{
	"frame": {"x":1742,"y":1032,"w":134,"h":129},
	"rotated": false,
	"trimmed": false,
	"spriteSourceSize": {"x":0,"y":0,"w":134,"h":129},
	"sourceSize": {"w":134,"h":129}
},
"Images_00134.png":
{
	"frame": {"x":1876,"y":1032,"w":134,"h":129},
	"rotated": false,
	"trimmed": false,
	"spriteSourceSize": {"x":0,"y":0,"w":134,"h":129},
	"sourceSize": {"w":134,"h":129}
},
"Images_00135.png":
{
	"frame": {"x":0,"y":1161,"w":134,"h":129},
	"rotated": false,
	"trimmed": false,
	"spriteSourceSize": {"x":0,"y":0,"w":134,"h":129},
	"sourceSize": {"w":134,"h":129}
},
"Images_00136.png":
{
	"frame": {"x":134,"y":1161,"w":134,"h":129},
	"rotated": false,
	"trimmed": false,
	"spriteSourceSize": {"x":0,"y":0,"w":134,"h":129},
	"sourceSize": {"w":134,"h":129}
},
"Images_00137.png":
{
	"frame": {"x":268,"y":1161,"w":134,"h":129},
	"rotated": false,
	"trimmed": false,
	"spriteSourceSize": {"x":0,"y":0,"w":134,"h":129},
	"sourceSize": {"w":134,"h":129}
},
"Images_00138.png":
{
	"frame": {"x":402,"y":1161,"w":134,"h":129},
	"rotated": false,
	"trimmed": false,
	"spriteSourceSize": {"x":0,"y":0,"w":134,"h":129},
	"sourceSize": {"w":134,"h":129}
},
"Images_00139.png":
{
	"frame": {"x":536,"y":1161,"w":134,"h":129},
	"rotated": false,
	"trimmed": false,
	"spriteSourceSize": {"x":0,"y":0,"w":134,"h":129},
	"sourceSize": {"w":134,"h":129}
},
"Images_00140.png":
{
	"frame": {"x":670,"y":1161,"w":134,"h":129},
	"rotated": false,
	"trimmed": false,
	"spriteSourceSize": {"x":0,"y":0,"w":134,"h":129},
	"sourceSize": {"w":134,"h":129}
},
"Images_00141.png":
{
	"frame": {"x":804,"y":1161,"w":134,"h":129},
	"rotated": false,
	"trimmed": false,
	"spriteSourceSize": {"x":0,"y":0,"w":134,"h":129},
	"sourceSize": {"w":134,"h":129}
},
"Images_00142.png":
{
	"frame": {"x":938,"y":1161,"w":134,"h":129},
	"rotated": false,
	"trimmed": false,
	"spriteSourceSize": {"x":0,"y":0,"w":134,"h":129},
	"sourceSize": {"w":134,"h":129}
},
"Images_00143.png":
{
	"frame": {"x":1072,"y":1161,"w":134,"h":129},
	"rotated": false,
	"trimmed": false,
	"spriteSourceSize": {"x":0,"y":0,"w":134,"h":129},
	"sourceSize": {"w":134,"h":129}
},
"Images_00144.png":
{
	"frame": {"x":1206,"y":1161,"w":134,"h":129},
	"rotated": false,
	"trimmed": false,
	"spriteSourceSize": {"x":0,"y":0,"w":134,"h":129},
	"sourceSize": {"w":134,"h":129}
},
"Images_00145.png":
{
	"frame": {"x":1340,"y":1161,"w":134,"h":129},
	"rotated": false,
	"trimmed": false,
	"spriteSourceSize": {"x":0,"y":0,"w":134,"h":129},
	"sourceSize": {"w":134,"h":129}
},
"Images_00146.png":
{
	"frame": {"x":1474,"y":1161,"w":134,"h":129},
	"rotated": false,
	"trimmed": false,
	"spriteSourceSize": {"x":0,"y":0,"w":134,"h":129},
	"sourceSize": {"w":134,"h":129}
},
"Images_00147.png":
{
	"frame": {"x":1608,"y":1161,"w":134,"h":129},
	"rotated": false,
	"trimmed": false,
	"spriteSourceSize": {"x":0,"y":0,"w":134,"h":129},
	"sourceSize": {"w":134,"h":129}
},
"Images_00148.png":
{
	"frame": {"x":1742,"y":1161,"w":134,"h":129},
	"rotated": false,
	"trimmed": false,
	"spriteSourceSize": {"x":0,"y":0,"w":134,"h":129},
	"sourceSize": {"w":134,"h":129}
},
"Images_00149.png":
{
	"frame": {"x":1876,"y":1161,"w":134,"h":129},
	"rotated": false,
	"trimmed": false,
	"spriteSourceSize": {"x":0,"y":0,"w":134,"h":129},
	"sourceSize": {"w":134,"h":129}
}},
"animations": {
	"Images": ["Images_00000.png","Images_00001.png","Images_00002.png","Images_00003.png","Images_00004.png","Images_00005.png","Images_00006.png","Images_00007.png","Images_00008.png","Images_00009.png","Images_00010.png","Images_00011.png","Images_00012.png","Images_00013.png","Images_00014.png","Images_00015.png","Images_00016.png","Images_00017.png","Images_00018.png","Images_00019.png","Images_00020.png","Images_00021.png","Images_00022.png","Images_00023.png","Images_00024.png","Images_00025.png","Images_00026.png","Images_00027.png","Images_00028.png","Images_00029.png","Images_00030.png","Images_00031.png","Images_00032.png","Images_00033.png","Images_00034.png","Images_00035.png","Images_00036.png","Images_00037.png","Images_00038.png","Images_00039.png","Images_00040.png","Images_00041.png","Images_00042.png","Images_00043.png","Images_00044.png","Images_00045.png","Images_00046.png","Images_00047.png","Images_00048.png","Images_00049.png","Images_00050.png","Images_00051.png","Images_00052.png","Images_00053.png","Images_00054.png","Images_00055.png","Images_00056.png","Images_00057.png","Images_00058.png","Images_00059.png","Images_00060.png","Images_00061.png","Images_00062.png","Images_00063.png","Images_00064.png","Images_00065.png","Images_00066.png","Images_00067.png","Images_00068.png","Images_00069.png","Images_00070.png","Images_00071.png","Images_00072.png","Images_00073.png","Images_00074.png","Images_00075.png","Images_00076.png","Images_00077.png","Images_00078.png","Images_00079.png","Images_00080.png","Images_00081.png","Images_00082.png","Images_00083.png","Images_00084.png","Images_00085.png","Images_00086.png","Images_00087.png","Images_00088.png","Images_00089.png","Images_00090.png","Images_00091.png","Images_00092.png","Images_00093.png","Images_00094.png","Images_00095.png","Images_00096.png","Images_00097.png","Images_00098.png","Images_00099.png","Images_00100.png","Images_00101.png","Images_00102.png","Images_00103.png","Images_00104.png","Images_00105.png","Images_00106.png","Images_00107.png","Images_00108.png","Images_00109.png","Images_00110.png","Images_00111.png","Images_00112.png","Images_00113.png","Images_00114.png","Images_00115.png","Images_00116.png","Images_00117.png","Images_00118.png","Images_00119.png","Images_00120.png","Images_00121.png","Images_00122.png","Images_00123.png","Images_00124.png","Images_00125.png","Images_00126.png","Images_00127.png","Images_00128.png","Images_00129.png","Images_00130.png","Images_00131.png","Images_00132.png","Images_00133.png","Images_00134.png","Images_00135.png","Images_00136.png","Images_00137.png","Images_00138.png","Images_00139.png","Images_00140.png","Images_00141.png","Images_00142.png","Images_00143.png","Images_00144.png","Images_00145.png","Images_00146.png","Images_00147.png","Images_00148.png","Images_00149.png"]
},
"meta": {
	"app": "https://www.codeandweb.com/texturepacker",
	"version": "1.0",
	"image": "joker.png",
	"format": "RGBA8888",
	"size": {"w":2010,"h":1290},
	"scale": "1",
	"smartupdate": "$TexturePacker:SmartUpdate:8dd63417507bbf122813f4f839b2601b:fc065271290921da788ea079e50687c2:103b26903d4fce67999f277d6afe6121$"
}
}
